reten_service_core/__init__.py
reten_service_core/auth/__init__.py
reten_service_core/auth/api_key.py
reten_service_core/auth/exceptions.py
reten_service_core/core/__init__.py
reten_service_core/core/settings.py
reten_service_core/logging/__init__.py
reten_service_core/logging/config.py
reten_service_core/storage/bigquery/README.md
reten_service_core/storage/bigquery/__init__.py
reten_service_core/storage/bigquery/client.py
reten_service_core-0.1.0.dist-info/METADATA
reten_service_core-0.1.0.dist-info/WHEEL
reten_service_core-0.1.0.dist-info/licenses/LICENSE
reten_service_core-0.1.0.dist-info/RECORD
