Metadata-Version: 2.4
Name: reten-service-core
Version: 0.1.0
Summary: Core library providing common components and utilities for Reten microservices
Author-email: Reten <dev@reten.ai>
License-Expression: MIT
License-File: LICENSE
Classifier: Development Status :: 3 - Alpha
Classifier: Intended Audience :: Developers
Classifier: License :: OSI Approved :: MIT License
Classifier: Programming Language :: Python :: 3
Classifier: Programming Language :: Python :: 3.10
Classifier: Programming Language :: Python :: 3.11
Classifier: Topic :: Software Development :: Libraries :: Python Modules
Requires-Python: >=3.10
Requires-Dist: fastapi>=0.100.0
Requires-Dist: google-cloud-bigquery>=3.11.0
Requires-Dist: pydantic-settings>=2.0.0
Requires-Dist: pydantic>=2.0.0
Requires-Dist: python-jose[cryptography]>=3.3.0
Requires-Dist: redis>=5.0.0
Requires-Dist: structlog>=23.1.0
Provides-Extra: dev
Requires-Dist: httpx>=0.24.0; extra == 'dev'
Requires-Dist: pre-commit>=3.3.0; extra == 'dev'
Requires-Dist: pydantic-settings>=2.0.0; extra == 'dev'
Requires-Dist: pytest-asyncio>=0.21.0; extra == 'dev'
Requires-Dist: pytest-cov>=4.1.0; extra == 'dev'
Requires-Dist: pytest>=7.4.0; extra == 'dev'
Requires-Dist: ruff>=0.1.5; extra == 'dev'
Requires-Dist: uvicorn>=0.23.0; extra == 'dev'
